py_fumen/__init__.py
py_fumen/action.py
py_fumen/comments.py
py_fumen/constants.py
py_fumen/decoder.py
py_fumen/defines.py
py_fumen/encoder.py
py_fumen/field.py
py_fumen/fumen_buffer.py
py_fumen/inner_field.py
py_fumen/js_escape.py
py_fumen/page.py
py_fumen/quiz.py
py_fumen-0.1.11.dist-info/METADATA
py_fumen-0.1.11.dist-info/WHEEL
py_fumen-0.1.11.dist-info/licenses/LICENSE
py_fumen-0.1.11.dist-info/RECORD
