Metadata-Version: 2.1
Name: py_fumen
Version: 0.1.11
Summary: A package that replicates js fumen in python. More description on 'https://github.com/hsohliyt105/py-fumen'
Project-URL: Homepage, https://github.com/hsohliyt105/py-fumen
Project-URL: Issues, https://github.com/hsohliyt105/py-fumen/issues
Author-email: hsohliyt105 <hsohliyt105@naver.com>
License-File: LICENSE
Classifier: License :: OSI Approved :: MIT License
Classifier: Operating System :: OS Independent
Classifier: Programming Language :: Python :: 3
Requires-Python: >=3.10
Requires-Dist: hatchling
